bytespace/__init__.py
bytespace/_interface.py
bytespace/exceptions.py
bytespace/interfaces.py
bytespace-1.1.0.dist-info/LICENSE
bytespace-1.1.0.dist-info/METADATA
bytespace-1.1.0.dist-info/WHEEL
bytespace-1.1.0.dist-info/top_level.txt
bytespace-1.1.0.dist-info/RECORD
