Metadata-Version: 2.1
Name: bytespace
Version: 1.1.0
Summary: A nice and simple API library for connecting to the bytespace API
Author: Remy
License: MIT License
Project-URL: Homepage, https://github.com/hrszpuk/bytespace.py
Keywords: bytespace,rect,tokorv,redcubedev,professordj,borgor
Classifier: License :: OSI Approved :: MIT License
Classifier: Programming Language :: Python
Classifier: Programming Language :: Python :: 3
Requires-Python: >=3.9
License-File: LICENSE
Requires-Dist: requests
